memory/__init__.py
memory/core.py
memory-1.0.0.dist-info/LICENSE
memory-1.0.0.dist-info/METADATA
memory-1.0.0.dist-info/WHEEL
memory-1.0.0.dist-info/top_level.txt
memory-1.0.0.dist-info/RECORD
